banner_sangwoo/__init__.py
banner_sangwoo/banner.py
banner_sangwoo-0.3.0.dist-info/METADATA
banner_sangwoo-0.3.0.dist-info/WHEEL
banner_sangwoo-0.3.0.dist-info/entry_points.txt
banner_sangwoo-0.3.0.dist-info/top_level.txt
banner_sangwoo-0.3.0.dist-info/RECORD
