Metadata-Version: 2.1
Name: banner_sangwoo
Version: 0.3.0
Summary: banner,picture,lotto program
Author-email: GITSangWoo <dogcenta@gmail.com>
License: MIT
Project-URL: Homepage, https://github.com/GITSangWoo/banner_sangwoo
Project-URL: Issues, https://github.com/GITSangWoo/banner_sangwoo/issues
Requires-Python: >=3.9
Requires-Dist: pyfiglet >=1.0.2
